[
  {
    "pfirstname": "Ep",
    "plastname": "Osvc",
    "ppoints": 5572
  },
  {
    "updated (JSON doesn't like comments):":"Fhwtde Bvmxqyyfvpis was updated. See result # 3, PID #240 in table_2",
    "pfirstname": "Fhwtde",
    "plastname": "Bvmxqyyfvpis",
    "ppoints": 5572
  },
  {
    "pfirstname": "Vzripewh",
    "plastname": "Kdvbeiutua",
    "ppoints": 5571
  },
  {
    "pfirstname": "Bimapxobsl",
    "plastname": "Vzh",
    "ppoints": 5570
  },
  {
    "pfirstname": "Hofsfavac",
    "plastname": "Ygufletouhkbv",
    "ppoints": 5569
  },
  {
    "pfirstname": "Wfsbvflqks",
    "plastname": "Mgbkoyibnaej",
    "ppoints": 5565
  },
  {
    "pfirstname": "Ut",
    "plastname": "Rkot",
    "ppoints": 5564
  },
  {
    "pfirstname": "Afjedkxithcu",
    "plastname": "Djevroebtrdh",
    "ppoints": 5563
  },
  {
    "pfirstname": "Lpmscisegq",
    "plastname": "Ystoatyrx",
    "ppoints": 5562
  },
  {
    "pfirstname": "Kigpsbjoje",
    "plastname": "Sxnced",
    "ppoints": 5561
  }
]